{
  "id": 20,
  "category": "advanced-slim-legs-training",
  "theme": "Advanced Slim Legs Training for Beginners",
  "tone": "professional",
  "title": "Everything You Need to Know About Advanced Slim Legs Training for Beginners",
  "slug": "everything-you-need-to-know-about-advanced-slim-legs-training-for-beginners",
  "meta_description": "Explore the fascinating world of Advanced Slim Legs Training for Beginners with our in-depth analysis. From beginner basics to advanced techniques, find everything you need to know.",
  "content": "Looking for a clear, easy-to-follow guide to Advanced Slim Legs Training for Beginners? This article is packed with actionable lists, step-by-step instructions, and practical tips you can start using right away. Let's dive in!\n\n<h3>Key Essentials</h3>\n<ul>\n  <li>Start with a solid foundation and build gradually</li>\n  <li>Focus on quality over quantity</li>\n  <li>Practice regularly for best results</li>\n  <li>Stay consistent and patient with progress</li>\n  <li>Never stop learning and improving</li>\n</ul>\n\n<h3>Getting Started</h3>\n<ul>\n  <li>Gather your essential resources first</li>\n  <li>Create a dedicated practice space</li>\n  <li>Set a realistic schedule you can follow</li>\n  <li>Track your progress to stay motivated</li>\n  <li>Join communities for support and inspiration</li>\n</ul>\n\n<h3>Common Challenges</h3>\n<ul>\n  <li>Finding the right approach for your needs</li>\n  <li>Staying motivated through the learning curve</li>\n  <li>Avoiding common mistakes and pitfalls</li>\n  <li>Balancing theory with practical application</li>\n  <li>Managing expectations and staying realistic</li>\n</ul>\n\n📌 **Quick Fact**: Interesting: Studies show that consistent practice yields 4x better results than occasional sessions.\n\n<h3>Success Principles</h3>\n<ul>\n  <li>Define clear goals before you start</li>\n  <li>Break complex tasks into manageable steps</li>\n  <li>Celebrate small wins along the way</li>\n  <li>Learn from mistakes and adapt quickly</li>\n  <li>Share knowledge and collaborate with others</li>\n</ul>\n\n📌 **Quick Fact**: Remarkable: Modern science is just beginning to understand why this is so effective.\n\n<h2>Why It Matters</h2>\n<p>Understanding the benefits helps us appreciate the value of this subject. In this section, we'll examine the positive impacts and advantages you can expect to gain from your learning journey.</p>\n<p>This is a key concept that deserves your full attention and practice.</p>\n<p>Learning is a journey, not a race—enjoy the process.</p>\n\n<h2>Essential Tools</h2>\n<p>What tools and resources should you be using? Let's explore the essential materials, tools, and resources that will support your learning and help you achieve your goals.</p>\n<p>This is a key concept that deserves your full attention and practice.</p>\n\n<h2>Practical Instructions</h2>\n<p>A systematic approach ensures you don't miss anything important. Here, we present the process in a logical sequence that builds momentum as you progress.</p>\n<p>Many people find that focusing on this aspect makes everything else easier.</p>\n<p>Celebrate your progress, no matter how small it may seem.</p>\n\n<h2>Common Misconceptions</h2>\n<p>Let's separate fact from fiction. There are many common misconceptions about this topic, and we're here to clarify them with accurate information and expert insights.</p>\n<p>This is one of the fundamental building blocks for future success.</p>\n\n<h2>Recommended Resources</h2>\n<p>What tools and resources should you be using? Let's explore the essential materials, tools, and resources that will support your learning and help you achieve your goals.</p>\n<p>Many people find that focusing on this aspect makes everything else easier.</p>\n<p>Learning is a journey, not a race—enjoy the process.</p>\n\n<h2>Practical Instructions</h2>\n<p>A systematic approach ensures you don't miss anything important. Here, we present the process in a logical sequence that builds momentum as you progress.</p>\n<p>Many people find that focusing on this aspect makes everything else easier.</p>\n\n<h2>Practical Instructions</h2>\n<p>Understanding this will significantly improve your overall approach and results.</p>\n<p>Let's break this down into manageable steps that anyone can follow. This comprehensive guide takes you from start to finish, explaining each phase clearly.</p>\n\n<h2>Next Level</h2>\n<p>Ready to take things to the next level? This section covers more advanced techniques and approaches for those who want to deepen their expertise and go beyond the basics.</p>\n\n<h2>Understanding Advanced Slim Legs Training for Beginners</h2>\n<p>Let's start with the basics: what exactly is this subject all about? We'll explore the core definitions and key concepts that form the foundation of this fascinating topic. Understanding these fundamentals is crucial for everything that follows.</p>\n<p>Understanding this will significantly improve your overall approach and results.</p>\n<p>Remember that consistency matters more than intensity.</p>\n\nAs we wrap up this guide on Advanced Slim Legs Training for Beginners, it's clear that this is a subject with depth and potential. We've covered the essentials, explored key concepts, and provided practical advice that you can start using immediately. Keep learning, keep practicing, and you'll continue to see progress and improvement over time. Thank you for joining us on this journey!",
  "created_at": "2026-06-05T15:48:07.636831",
  "word_count": 658,
  "seo": {
    "keywords": [
      "advanced slim legs training for beginners",
      "advanced-slim-legs-training",
      "Advanced Slim Legs Training for Beginners guide",
      "best Advanced Slim Legs Training for Beginners",
      "Advanced Slim Legs Training for Beginners tips",
      "Advanced Slim Legs Training for Beginners 2026",
      "how to advanced slim legs training for beginners"
    ],
    "title_tag": "Everything You Need to Know About Advanced Slim Legs Training for Beginners | slim-legs-training",
    "meta_description": "Explore the fascinating world of Advanced Slim Legs Training for Beginners with our in-depth analysis. From beginner basics to advanced techniques, find everything you need to know.",
    "og_title": "Everything You Need to Know About Advanced Slim Legs Training for Beginners",
    "og_description": "Explore the fascinating world of Advanced Slim Legs Training for Beginners with our in-depth analysis. From beginner basics to advanced techniques, find everything you need to know.",
    "og_type": "article",
    "twitter_card": "summary_large_image",
    "canonical_url": "/everything-you-need-to-know-about-advanced-slim-legs-training-for-beginners",
    "robots": "index, follow"
  },
  "geo": {
    "country": "Canada",
    "city": "Toronto",
    "language": "en",
    "target_regions": [
      "North America",
      "Europe",
      "Asia Pacific"
    ]
  },
  "image": {
    "id": "7f56c061c7a8f1c6d484cfedaf8c443d8a0fe53210473949d6040017c5744f5a",
    "url": "https://picsum.photos/973/510?random=529",
    "alt": "Featured image for: Everything You Need to Know About Advanced Slim Legs Training for Beginners",
    "width": 973,
    "height": 510
  }
}